groupdocs_parser_cloud/__init__.py
groupdocs_parser_cloud/api_client.py
groupdocs_parser_cloud/api_exception.py
groupdocs_parser_cloud/auth.py
groupdocs_parser_cloud/configuration.py
groupdocs_parser_cloud/rest.py
groupdocs_parser_cloud/apis/__init__.py
groupdocs_parser_cloud/apis/file_api.py
groupdocs_parser_cloud/apis/folder_api.py
groupdocs_parser_cloud/apis/info_api.py
groupdocs_parser_cloud/apis/parse_api.py
groupdocs_parser_cloud/apis/storage_api.py
groupdocs_parser_cloud/apis/template_api.py
groupdocs_parser_cloud/models/__init__.py
groupdocs_parser_cloud/models/barcode.py
groupdocs_parser_cloud/models/barcode_page.py
groupdocs_parser_cloud/models/barcodes_options.py
groupdocs_parser_cloud/models/barcodes_result.py
groupdocs_parser_cloud/models/container_item.py
groupdocs_parser_cloud/models/container_item_info.py
groupdocs_parser_cloud/models/container_options.py
groupdocs_parser_cloud/models/container_result.py
groupdocs_parser_cloud/models/coordinates.py
groupdocs_parser_cloud/models/create_template_options.py
groupdocs_parser_cloud/models/detector_parameters.py
groupdocs_parser_cloud/models/disc_usage.py
groupdocs_parser_cloud/models/error.py
groupdocs_parser_cloud/models/error_details.py
groupdocs_parser_cloud/models/field.py
groupdocs_parser_cloud/models/field_data.py
groupdocs_parser_cloud/models/field_position.py
groupdocs_parser_cloud/models/file_info.py
groupdocs_parser_cloud/models/file_type.py
groupdocs_parser_cloud/models/file_version.py
groupdocs_parser_cloud/models/file_versions.py
groupdocs_parser_cloud/models/files_list.py
groupdocs_parser_cloud/models/files_upload_result.py
groupdocs_parser_cloud/models/format.py
groupdocs_parser_cloud/models/formats_result.py
groupdocs_parser_cloud/models/formatted_text_options.py
groupdocs_parser_cloud/models/image.py
groupdocs_parser_cloud/models/image_page.py
groupdocs_parser_cloud/models/images_options.py
groupdocs_parser_cloud/models/images_result.py
groupdocs_parser_cloud/models/info_options.py
groupdocs_parser_cloud-25.10.dist-info/licenses/LICENSE
groupdocs_parser_cloud-25.10.dist-info/METADATA
groupdocs_parser_cloud-25.10.dist-info/WHEEL
groupdocs_parser_cloud-25.10.dist-info/top_level.txt
groupdocs_parser_cloud-25.10.dist-info/RECORD
